logredactor/__init__.py
logredactor/redacting_filter.py
logredactor-0.0.2.dist-info/LICENSE
logredactor-0.0.2.dist-info/METADATA
logredactor-0.0.2.dist-info/WHEEL
logredactor-0.0.2.dist-info/top_level.txt
logredactor-0.0.2.dist-info/RECORD
