Metadata-Version: 2.1
Name: logredactor
Version: 0.0.2
Summary: Redact logs based on regex filters
Home-page: https://github.com/xtream1101/logredactor
License: UNKNOWN
Platform: UNKNOWN
License-File: LICENSE
